dagmc_h5m_file_inspector/__init__.py
dagmc_h5m_file_inspector/_version.py
dagmc_h5m_file_inspector/core.py
dagmc_h5m_file_inspector-0.5.0.data/scripts/inspect-dagmc-h5m-file
dagmc_h5m_file_inspector-0.5.0.dist-info/LICENSE.txt
dagmc_h5m_file_inspector-0.5.0.dist-info/METADATA
dagmc_h5m_file_inspector-0.5.0.dist-info/WHEEL
dagmc_h5m_file_inspector-0.5.0.dist-info/top_level.txt
dagmc_h5m_file_inspector-0.5.0.dist-info/RECORD
