Metadata-Version: 2.1
Name: dagmc-h5m-file-inspector
Version: 0.5.0
Summary: Extracts information from DAGMC h5m files including volumes number, material tags
Home-page: https://github.com/fusion-energy/dagmc_h5m_file_inspector
Author: The dagmc_h5m_file_inspector Development Team
Author-email: mail@jshimwell.com
License: MIT
Project-URL: Source, https://github.com/fusion-energy/dagmc_h5m_file_inspector
Project-URL: Tracker, https://github.com/fusion-energy/dagmc_h5m_file_inspector/issues
Platform: UNKNOWN
Classifier: Natural Language :: English
Classifier: Topic :: Scientific/Engineering
Classifier: Programming Language :: Python :: 3
Classifier: Programming Language :: Python :: 3.6
Classifier: Programming Language :: Python :: 3.7
Classifier: Programming Language :: Python :: 3.8
Classifier: Programming Language :: Python :: 3.9
Classifier: License :: OSI Approved :: MIT License
Classifier: Operating System :: OS Independent
Requires-Python: >=3.6
License-File: LICENSE.txt
Provides-Extra: tests
Requires-Dist: pytest (>=5.4.3) ; extra == 'tests'
Requires-Dist: requests ; extra == 'tests'
Requires-Dist: pytest-cov ; extra == 'tests'
